Metadata-Version: 2.1
Name: JD-SDK-CUSTOM
Version: 0.0.4
Summary: JD SDK version 2.0
Home-page: UNKNOWN
Author: Rponnt
Author-email: rponnt@gmail.com
License: UNKNOWN
Platform: UNKNOWN
Classifier: Programming Language :: Python :: 3
Classifier: License :: OSI Approved :: MIT License
Requires-Python: >=3
Requires-Dist: numpy
Requires-Dist: rsa
Requires-Dist: psutil
Requires-Dist: apscheduler
Requires-Dist: wincertstore
